service_auth/__init__.py
service_auth/admin.py
service_auth/apps.py
service_auth/permissions.py
service_auth/remote_model.py
service_auth/views.py
service_auth/migrations/__init__.py
dj_micro_auth_connect-0.5.2.dist-info/LICENSE
dj_micro_auth_connect-0.5.2.dist-info/METADATA
dj_micro_auth_connect-0.5.2.dist-info/WHEEL
dj_micro_auth_connect-0.5.2.dist-info/top_level.txt
dj_micro_auth_connect-0.5.2.dist-info/RECORD
