Metadata-Version: 2.1
Name: dj-micro-auth-connect
Version: 0.5.2
Summary: A small package to connect microservices and authenticate user.
Home-page: https://github.com/krishna-bhandari/dj_micro_auth_connect
Author: Krishna Bhandari
Author-email: author@example.com
License: UNKNOWN
Project-URL: Bug Tracker, https://github.com/krishna-bhandari/dj_micro_auth_connect/issues
Platform: UNKNOWN
Classifier: Programming Language :: Python :: 3
Classifier: License :: OSI Approved :: MIT License
Classifier: Operating System :: OS Independent
Requires-Python: >=3.6
License-File: LICENSE
Requires-Dist: djangorestframework (>=3.12.4)
Requires-Dist: requests (>=2.26.0)
